pythonUtilities/__init__.py
pythonUtilities-0.0.1.dist-info/LICENCE
pythonUtilities-0.0.1.dist-info/METADATA
pythonUtilities-0.0.1.dist-info/WHEEL
pythonUtilities-0.0.1.dist-info/top_level.txt
pythonUtilities-0.0.1.dist-info/RECORD
